[
    {
        "NOME": "PR HÉLIO",
        "CLUBE": "ORGANIZAÇÃO",
        "IGREJA": "CENTRAL",
        "DISTRITO": "APAC",
        "DATA DE NASCIMENTO": "1989-05-17",
        "CELULAR": "(19) 9100-5260",
        "E-MAIL": "JEFERSONCONQUISTADOR@HOTMAIL.COM"
    },
    {
        "NOME": "PAULO VICTOR",
        "CLUBE": "ANJOS DO ADVENTO",
        "IGREJA": "JARDIM SANTA CRUZ",
        "DISTRITO": "SOCORRO",
        "DATA DE NASCIMENTO": "2025-02-15",
        "CELULAR": "(83) 8826-4722",
        "E-MAIL": "ITALO@HOTMAIL.COM"
    },
    {
        "NOME": "ADRIANO FERNANDES",
        "CLUBE": "SEMEADORES",
        "IGREJA": "PQ. DOS TRABALHADORES",
        "DISTRITO": "ARTUR NOUGUEIRA",
        "DATA DE NASCIMENTO": "1998-02-15",
        "CELULAR": "(19) 99711-8877",
        "E-MAIL": "ITALO@HOTMAIL.COM"
    },
    {
        "NOME": "LEONILDO",
        "CLUBE": "FORTALEZA DO VALE",
        "IGREJA": "CHAPARRAL",
        "DISTRITO": "JARDIM NOVO 2",
        "DATA DE NASCIMENTO": "2025-02-15",
        "CELULAR": "(19) 99134-6091",
        "E-MAIL": "ITALO@HOTMAIL.COM"
    },
    {
        "NOME": "ITALO ARAÚJO",
        "CLUBE": "BARÃO DO REINO",
        "IGREJA": "BARÃO GERALDO",
        "DISTRITO": "BARÃO GERALDO",
        "DATA DE NASCIMENTO": "2025-02-15",
        "CELULAR": "(83) 8826-4722",
        "E-MAIL": "ITALO@HOTMAIL.COM"
    },
    {
        "NOME": "EDIRLEI SILVA",
        "CLUBE": "PORTO SEGURO",
        "IGREJA": "ITATIBA",
        "DISTRITO": "ITATIBA",
        "DATA DE NASCIMENTO": "2025-02-15",
        "CELULAR": "(83) 8826-4722",
        "E-MAIL": "ITALO@HOTMAIL.COM"
    },
    {
        "NOME": "JERFERSON GERSON DOS SANTOS NASCIMENTO",
        "CLUBE": "ESTRELA DO ORIENTE",
        "IGREJA": "AMERICANA CENTRAL",
        "DISTRITO": "AMERICANA",
        "DATA DE NASCIMENTO": "1989-05-17",
        "CELULAR": "(19) 9100-5260",
        "E-MAIL": "JEFERSONCONQUISTADOR@HOTMAIL.COM"
    },
    {
        "NOME": "ANTONIO NERI DA SILVA",
        "CLUBE": "ÔNIX",
        "IGREJA": "JD. BOER",
        "DISTRITO": "AMERICANA",
        "DATA DE NASCIMENTO": "1963-05-13",
        "CELULAR": "(66) 9662-0916",
        "E-MAIL": "ANTONIO@GMAIL.COM"
    },
    {
        "NOME": "PAULO SERGIO DA SILVA",
        "CLUBE": "ÁGUIA DOS LÍRIOS",
        "IGREJA": "JD. DOS LÍRIOS",
        "DISTRITO": "AMERICANA",
        "DATA DE NASCIMENTO": "1969-05-17",
        "CELULAR": "19.983.873.909",
        "E-MAIL": "P.SERGIO.SILVA2010@BOL.COM.BR"
    },
    {
        "NOME": "VAGNER PINTO DO PRADO",
        "CLUBE": "CONQUISTADORES",
        "IGREJA": "B. SÃO MANOEL",
        "DISTRITO": "B. SÃO MANOEL",
        "DATA DE NASCIMENTO": "1990-06-17",
        "CELULAR": "(19) 99182-4999",
        "E-MAIL": "VAGNER.P.PRADO@HOTMAIL.COM"
    },
    {
        "NOME": "JAQUELINE",
        "CLUBE": "REVELADORES DO REI",
        "IGREJA": "JARDIM SÃO PEDRO",
        "DISTRITO": "SÃO PEDRO",
        "DATA DE NASCIMENTO": "1990-06-17",
        "CELULAR": "(19) 99903-1633",
        "E-MAIL": "JAQUELINEPRADO909@GMAIL.COM"
    },
    {
        "NOME": "AMÓS GOMES",
        "CLUBE": "CARAVELA",
        "IGREJA": "TAQUARAL",
        "DISTRITO": "CASTELO",
        "DATA DE NASCIMENTO": "2025-01-17",
        "CELULAR": " (91) 98431-9511",
        "E-MAIL": "CARAVELADBV@GMAIL.COM"
    },
    {
        "NOME": "VICTOR MOBILLON LEVI",
        "CLUBE": "SENTINELLAS",
        "IGREJA": "JD. DA PAZ",
        "DISTRITO": "B. SÃO MANOEL",
        "DATA DE NASCIMENTO": "1999-01-15",
        "CELULAR": "19.996.272.990",
        "E-MAIL": "VICTOR_MLEVI@HOTMAIL.COM"
    },
    {
        "NOME": "EVELYN CAROLINE FONTENELE DE PAULA",
        "CLUBE": "ALPHA CENTAURO",
        "IGREJA": "VALE DAS NOGUEIRAS",
        "DISTRITO": "B. SÃO MANOEL",
        "DATA DE NASCIMENTO": "1994-12-03",
        "CELULAR": "19935005832",
        "E-MAIL": "EVELLYN.FF.FONTENELE@GMAIL.COM"
    },
    {
        "NOME": "SABRINA ALVES DA SILVA PAIXÃO",
        "CLUBE": "LIBERTADORES",
        "IGREJA": "IRACEMAPOLIS",
        "DISTRITO": "JD. MORRO BRANCO",
        "DATA DE NASCIMENTO": "2000-07-29",
        "CELULAR": "75991808624",
        "E-MAIL": "SABRINA.ALVES11@OUTLOOK.COM"
    },
    {
        "NOME": "YNGRID MIKAELE SANTANA SILVA",
        "CLUBE": "HATIKVAH",
        "IGREJA": "JD. MORRO BRANCO",
        "DISTRITO": "JD. MORRO BRANCO",
        "DATA DE NASCIMENTO": "2004-06-04",
        "CELULAR": "996526305",
        "E-MAIL": "YNGRIDMIKAELE373@GMAIL.COM"
    },
    {
        "NOME": "BRUNA NARA MOURA CORDEIRO",
        "CLUBE": "PIONEIROS DA ALEGRIA",
        "IGREJA": "PQ. NOSSA SENHORA DAS DORES",
        "DISTRITO": "JD. MORRO BRANCO",
        "DATA DE NASCIMENTO": "1987-04-28",
        "CELULAR": "983429544",
        "E-MAIL": "BRUNANARAMOURA@GMAIL.COM"
    },
    {
        "NOME": "LÚCIO ROCHA MODESTO JÚNIOR",
        "CLUBE": "ÁGUIA DO REINO",
        "IGREJA": "JD. NOVA SUIÇA",
        "DISTRITO": "JD. OLGA VERONI/LIM.",
        "DATA DE NASCIMENTO": "2002-10-04",
        "CELULAR": "(19) 987347441",
        "E-MAIL": "LUCIOJRDEBOAS@GMAIL.COM"
    },
    {
        "NOME": "BRUNA CIPRIANO",
        "CLUBE": "ÁGUIAS DO HORIZONTE",
        "IGREJA": "JD. NOVO HORIZONTE - LIMEIRA",
        "DISTRITO": "JD. OLGA VERONI/LIM.",
        "DATA DE NASCIMENTO": "1986-04-24",
        "CELULAR": "19981423266",
        "E-MAIL": "BRUNACIPRIANOBRUNA@GMAIL.COM"
    },
    {
        "NOME": "ADEMIR JARDIM DOS SANTOS",
        "CLUBE": "ÁGUIA AVANTE",
        "IGREJA": "JD. OLGA VERONI/LIM.",
        "DISTRITO": "JD. OLGA VERONI/LIM.",
        "DATA DE NASCIMENTO": "1963-04-12",
        "CELULAR": "11984730225",
        "E-MAIL": "DBVAGUIAAVANTE@GMAIL.COM"
    },
    {
        "NOME": "RAFAELA SOUZA PEREIRA",
        "CLUBE": "GUARDIÕES DO REI",
        "IGREJA": "PQ. HIPOLITO",
        "DISTRITO": "JD. OLGA VERONI/LIM.",
        "DATA DE NASCIMENTO": "1990-11-14",
        "CELULAR": "19-984469333",
        "E-MAIL": "RAFAELASOUZA.HAYLLA@GMAIL.COM"
    },
    {
        "NOME": "RODRIGO SARE",
        "CLUBE": "ÁGUIA DOS ALPES",
        "IGREJA": "JD. AEROPORTO/LIM.",
        "DISTRITO": "JD. SÃO JOÃO - LIMEIRA",
        "DATA DE NASCIMENTO": "1989-07-20",
        "CELULAR": "019983302058",
        "E-MAIL": "RODRIGO@GMAIL.COM"
    },
    {
        "NOME": "EUNICE DE SOUZA OLIVEIRA",
        "CLUBE": "VALDENSES",
        "IGREJA": "JD. SANTINA",
        "DISTRITO": "JD. SÃO JOÃO - LIMEIRA",
        "DATA DE NASCIMENTO": "1983-07-13",
        "CELULAR": "19996927742",
        "E-MAIL": "EUNICELAIF@GMAIL.COM"
    },
    {
        "NOME": "JHONATA WILLIAN MAIA ANDRIGHETI",
        "CLUBE": "GUERREIROS DA MONTANHA",
        "IGREJA": "JD. SÃO JOÃO",
        "DISTRITO": "JD. SÃO JOÃO - LIMEIRA",
        "DATA DE NASCIMENTO": "1995-06-08",
        "CELULAR": "(19) 98149-2119",
        "E-MAIL": "JHWWILL5@GMAIL.COM"
    },
    {
        "NOME": "JOÉLIA AZEVEDO DE OLIVEIRA PEREIRA",
        "CLUBE": "ATALAIA",
        "IGREJA": "LIMEIRA CENTRAL",
        "DISTRITO": "LIMEIRA CENTRAL",
        "DATA DE NASCIMENTO": "1981-11-04",
        "CELULAR": "(19)99980-5354",
        "E-MAIL": "JOELIAAZPEREIRA@HOTMAIL.COM"
    },
    {
        "NOME": "VINÍCIUS PETERSEN BRANDÃO",
        "CLUBE": "EXPLORADORES DE LIMEIRA",
        "IGREJA": "LIMEIRA CENTRAL",
        "DISTRITO": "LIMEIRA CENTRAL",
        "DATA DE NASCIMENTO": "1999-05-26",
        "CELULAR": "999712173",
        "E-MAIL": "VYNNYPETERSEN@GMAIL.COM"
    },
    {
        "NOME": "CLEBER AUGUSTO OLIVEIRA",
        "CLUBE": "ÁGUIA DOURADA",
        "IGREJA": "B. CIDADE NOVA/S.B.O.",
        "DISTRITO": "SANTA BARBARA D`OESTE",
        "DATA DE NASCIMENTO": "1985-04-06",
        "CELULAR": "19971063129",
        "E-MAIL": "CLEBINHOAUGUSTO15@GMAIL.COM"
    },
    {
        "NOME": "JOSIVAL SANTOS ALEXANDRE",
        "CLUBE": "CRUZEIRO DO SUL",
        "IGREJA": "JD. EUROPA/S.B.O",
        "DISTRITO": "SANTA BARBARA D`OESTE",
        "DATA DE NASCIMENTO": "1986-09-20",
        "CELULAR": "989539878",
        "E-MAIL": "JOSIVALSNTS50@GMAIL.COM"
    },
    {
        "NOME": "MOACIR MOREIRA GOMES",
        "CLUBE": "CASTELO FORTE",
        "IGREJA": "SANTA BARBARA D`OESTE",
        "DISTRITO": "SANTA BARBARA D`OESTE",
        "DATA DE NASCIMENTO": "1974-11-25",
        "CELULAR": "19999455653",
        "E-MAIL": "MOACIRMGOMES@HOTMAIL.COM"
    },
    {
        "NOME": "JOSÉ DOS REIS JUNIOR",
        "CLUBE": "LEÕES DO REI",
        "IGREJA": "VILA MOLLON",
        "DISTRITO": "SANTA BARBARA D`OESTE",
        "DATA DE NASCIMENTO": "1969-09-01",
        "CELULAR": "01998363-8963",
        "E-MAIL": "JREIS7794@GMAIL.COM"
    },
    {
        "NOME": "BRUNO FRADESCHI MASTELLARI",
        "CLUBE": "GUARDIÕES DA FÉ",
        "IGREJA": "VILA RICA",
        "DISTRITO": "SANTA BARBARA D`OESTE",
        "DATA DE NASCIMENTO": "1985-01-27",
        "CELULAR": "19991428254",
        "E-MAIL": "BRUNO_MASTELLARI@HOTMAIL.COM"
    },
    {
        "NOME": "GEAN DA SILVA GONÇALVES",
        "CLUBE": "LEÕES DO CAJ",
        "IGREJA": "AGAPEAMA/JUNDIAÍ",
        "DISTRITO": "AGAPEAMA/JUNDIAÍ",
        "DATA DE NASCIMENTO": "1995-03-23",
        "CELULAR": "75992215532",
        "E-MAIL": "JEANSILVA.MISSIONARIO@GMAIL.COM"
    },
    {
        "NOME": "NOELI JOLO JUSTINO DOS SANTOS",
        "CLUBE": "ÓRION",
        "IGREJA": "AGAPEAMA/JUNDIAÍ",
        "DISTRITO": "AGAPEAMA/JUNDIAÍ",
        "DATA DE NASCIMENTO": "1982-09-15",
        "CELULAR": "(11) 7265-0478",
        "E-MAIL": "NOELIJOLO@YAHOO.COM.BR"
    },
    {
        "NOME": "TATIANE MARA DE OLIVEIRA",
        "CLUBE": "300",
        "IGREJA": "JD. ESPLANADA",
        "DISTRITO": "AGAPEAMA/JUNDIAÍ",
        "DATA DE NASCIMENTO": "1979-12-16",
        "CELULAR": "11995706230",
        "E-MAIL": "TATIMARA2011@HOTMAIL.COM"
    },
    {
        "NOME": "ZAQUEU JOSE NASCIMENTO",
        "CLUBE": "ROCHA DOS SÉCULOS",
        "IGREJA": "ÁGUAS DE LINDÓIA",
        "DISTRITO": "ÁGUAS DE LINDÓIA",
        "DATA DE NASCIMENTO": "1953-04-20",
        "CELULAR": "19.982.679.060",
        "E-MAIL": "ROCHADOSSECULOS.DESBRAVADORES@GMAIL.COM"
    },
    {
        "NOME": "TALITA MARIA FERRARI DE SOUZA",
        "CLUBE": "VALE DAS ÁGUAS",
        "IGREJA": "LINDOIA",
        "DISTRITO": "ÁGUAS DE LINDÓIA",
        "DATA DE NASCIMENTO": "1988-10-17",
        "CELULAR": "19971322156",
        "E-MAIL": "TALITAFERRARI.TATA@GMAIL.COM"
    },
    {
        "NOME": "ALINE CARLA DE OLIVEIRA DIAS",
        "CLUBE": "SERRA NEGRA",
        "IGREJA": "SERRA NEGRA",
        "DISTRITO": "ÁGUAS DE LINDÓIA",
        "DATA DE NASCIMENTO": "1989-10-25",
        "CELULAR": "(19) 99722-1464",
        "E-MAIL": "NINIBOMBOM2@GMAIL.COM"
    },
    {
        "NOME": "ANDREIA MAGGI VIEIRA",
        "CLUBE": "ÓRION II",
        "IGREJA": "ARARAS CENTRAL",
        "DISTRITO": "ARARAS",
        "DATA DE NASCIMENTO": "1983-04-11",
        "CELULAR": "19981164332",
        "E-MAIL": "DREIAMAGGI@HOTMAIL.COM"
    },
    {
        "NOME": "VILSON HELOM POIER",
        "CLUBE": "AMIGOS DO PARAÍSO",
        "IGREJA": "ARTUR NOGUEIRA CENTRAL",
        "DISTRITO": "ARTUR NOGUEIRA CENTRAL",
        "DATA DE NASCIMENTO": "1974-05-02",
        "CELULAR": "19.981.401.417",
        "E-MAIL": "HELOMPOIER@HOTMAIL.COM"
    },
    {
        "NOME": "ANA MANOELA REIS RIOS  PEREIRA",
        "CLUBE": "HIMALAIA",
        "IGREJA": "B. JOSE OMETTO",
        "DISTRITO": "B. JOSE OMETTO",
        "DATA DE NASCIMENTO": "1987-11-11",
        "CELULAR": "(19) 8323-3624",
        "E-MAIL": "JORNALISTA.ANAMANOELA@GMAIL.COM"
    },
    {
        "NOME": "MIGUEL LLASE AUGUSTO",
        "CLUBE": "ÁGUIA DO LESTE",
        "IGREJA": "JD. MIRIAM",
        "DISTRITO": "B. JOSE OMETTO",
        "DATA DE NASCIMENTO": "2006-03-23",
        "CELULAR": "(19) 996378221",
        "E-MAIL": "MIGUELITOLLASE@GMAIL.COM"
    },
    {
        "NOME": "VITÓRIA SANTIAGO ROSA DE SOUZA",
        "CLUBE": "CONQUISTADORES DA PAZ",
        "IGREJA": "B. MATÃO",
        "DISTRITO": "B. MATÃO / SUMARÉ",
        "DATA DE NASCIMENTO": "2004-05-01",
        "CELULAR": "19983394883",
        "E-MAIL": "VITORIASANTIAGOSOUZA04@GMAIL.COM"
    },
    {
        "NOME": "MANOEL RAIMUNDO PACHECO CAMPOS",
        "CLUBE": "HERÓIS DO ADVENTO",
        "IGREJA": "JD. MINESOTA",
        "DISTRITO": "B. MATÃO / SUMARÉ",
        "DATA DE NASCIMENTO": "1976-03-29",
        "CELULAR": "1998840-2272",
        "E-MAIL": "MANOEL2903@GMAIL.COM"
    },
    {
        "NOME": "JOSE MARCELO VITOR",
        "CLUBE": "ANJOS DO PARAISO",
        "IGREJA": "JD. PARAÍSO",
        "DISTRITO": "B. MATÃO / SUMARÉ",
        "DATA DE NASCIMENTO": "1976-11-17",
        "CELULAR": "(19) 989395794",
        "E-MAIL": "MARCELOVITOR201125@GMAIL.COM"
    },
    {
        "NOME": "EDSON MENDES DE SOUZA",
        "CLUBE": "TRIBOS DE ISRAEL",
        "IGREJA": "JD. SÃO GERÔNIMO",
        "DISTRITO": "B. MATÃO / SUMARÉ",
        "DATA DE NASCIMENTO": "1970-01-15",
        "CELULAR": "19982588371",
        "E-MAIL": "EMSROS@IG.COM.BR"
    },
    {
        "NOME": "RUTE DOS SANTOS DA CONCEIÇÃO",
        "CLUBE": "ÁGUIAS DO OLÍMPIA",
        "IGREJA": "VILA OLÍMPIA",
        "DISTRITO": "B. MATÃO / SUMARÉ",
        "DATA DE NASCIMENTO": "1983-03-16",
        "CELULAR": "",
        "E-MAIL": "RUTE@GMAIL.COM"
    },
    {
        "NOME": "ANDERSON MAGALHÃES DOS SANTOS",
        "CLUBE": "GALILÉIA",
        "IGREJA": "JD. CAMPO BELO 1",
        "DISTRITO": "BAIRRO CIDADE SINGER",
        "DATA DE NASCIMENTO": "1992-11-20",
        "CELULAR": "(19) 98993-9953",
        "E-MAIL": "ANDERSONMGLDS@GMAIL.COM"
    },
    {
        "NOME": "SILMAR DOS SANTOS DO NASCIMENTO",
        "CLUBE": "GUERREIROS DE ISRAEL",
        "IGREJA": "JD. CAMPO BELO 1",
        "DISTRITO": "BAIRRO CIDADE SINGER",
        "DATA DE NASCIMENTO": "1978-07-02",
        "CELULAR": "(55) 19992-2057",
        "E-MAIL": "SILMARSANTOS29@GMAIL.COM"
    },
    {
        "NOME": "VINICIUS AMARO DA SILVA",
        "CLUBE": "ROCHA ETERNA",
        "IGREJA": "JD. CAMPO BELO 2",
        "DISTRITO": "BAIRRO CIDADE SINGER",
        "DATA DE NASCIMENTO": "2006-01-30",
        "CELULAR": "987667733",
        "E-MAIL": "SILAMAROVINI@GMAIL.COM"
    },
    {
        "NOME": "RAPHAEL NERY KUASNE",
        "CLUBE": "MANDADOS DE DEUS",
        "IGREJA": "JD. CIDADE UNIVERSITÁRIA",
        "DISTRITO": "BAIRRO CIDADE SINGER",
        "DATA DE NASCIMENTO": "1988-09-27",
        "CELULAR": "(19) 9884-88784",
        "E-MAIL": "CRIZKUASNE@HOTMAIL.COM"
    },
    {
        "NOME": "ETIENE DILDER SOUSA DE NASARÉ",
        "CLUBE": "PORTAL DE ÓRION",
        "IGREJA": "JD. MARISA",
        "DISTRITO": "BAIRRO CIDADE SINGER",
        "DATA DE NASCIMENTO": "1985-06-13",
        "CELULAR": "19988561107",
        "E-MAIL": "ETIENE2813@GMAIL.COM"
    },
    {
        "NOME": "ULISSES  RODRIGUES",
        "CLUBE": "TIGRES D ALVA",
        "IGREJA": "JD. SAO DOMINGOS",
        "DISTRITO": "BAIRRO CIDADE SINGER",
        "DATA DE NASCIMENTO": "1987-07-23",
        "CELULAR": "(19)98931-4064",
        "E-MAIL": "ULISSES.CB1@GMAIL.COM"
    },
    {
        "NOME": "LEONARDO HENRIQUE ARRUDA DE SOUZA",
        "CLUBE": "MARATON",
        "IGREJA": "BARÃO GERALDO",
        "DISTRITO": "BARÃO GERALDO",
        "DATA DE NASCIMENTO": "1997-05-25",
        "CELULAR": "19 98310-3431",
        "E-MAIL": "PILGRIMOPEREGRINO@GMAIL.COM"
    },
    {
        "NOME": "THIAGO DOS SANTOS",
        "CLUBE": "RIGEL",
        "IGREJA": "JARDIM SANTA MÔNICA",
        "DISTRITO": "BARÃO GERALDO",
        "DATA DE NASCIMENTO": "1983-06-25",
        "CELULAR": "997763130",
        "E-MAIL": "PCP1_KANON@HOTMAIL.COM"
    },
    {
        "NOME": "FLAVISON MIQUEIAS SERAFIM SANTOS",
        "CLUBE": "GUERREIROS DA ESPERANÇA",
        "IGREJA": "VILA ESPERANÇA",
        "DISTRITO": "BARÃO GERALDO",
        "DATA DE NASCIMENTO": "2005-07-24",
        "CELULAR": "(11) 95799-3399",
        "E-MAIL": "FLAVISONSANTOS57@GMAIL.COM"
    },
    {
        "NOME": "CRISTHIAN CALDERON RODRIGUEZ",
        "CLUBE": "ANDORINHAS",
        "IGREJA": "CAMPINAS CENTRAL",
        "DISTRITO": "CAMPINAS CENTRAL",
        "DATA DE NASCIMENTO": "1990-04-14",
        "CELULAR": "925996663",
        "E-MAIL": "CRISTHIAN.WCR@HOTMAIL.COM"
    },
    {
        "NOME": "JOÃO PAULO FERNANDES MAGALHÃES",
        "CLUBE": "ASAS DA LIBERDADE",
        "IGREJA": "CAMPO LIMPO PAULISTA",
        "DISTRITO": "CAMPO LIMPO PAULISTA",
        "DATA DE NASCIMENTO": "1997-03-10",
        "CELULAR": "(11) 7548-2039",
        "E-MAIL": "JP_VERDAO@ICLOUD.COM"
    },
    {
        "NOME": "WASHINGTON AVELINO FERREIRA FURLAN",
        "CLUBE": "CASTELO",
        "IGREJA": "CASTELO",
        "DISTRITO": "CASTELO",
        "DATA DE NASCIMENTO": "1980-01-03",
        "CELULAR": "(19) 99796-2551",
        "E-MAIL": "WASHINGTON.FURLAN@ADVENTISTAS.ORG"
    },
    {
        "NOME": "IRENE VITORIANO DIAS",
        "CLUBE": "CARC",
        "IGREJA": "B. BELA VISTA/RIO CLARO",
        "DISTRITO": "CERVEZON",
        "DATA DE NASCIMENTO": "1979-07-07",
        "CELULAR": "(19)996983907",
        "E-MAIL": "IRENEVITSILVA@YAHOO.COM.BR"
    },
    {
        "NOME": "SILMARA REGINA DIOLINO",
        "CLUBE": "NAVEGANTES",
        "IGREJA": "CERVEZON",
        "DISTRITO": "CERVEZON",
        "DATA DE NASCIMENTO": "1980-12-31",
        "CELULAR": "996996738",
        "E-MAIL": "SILMARA.R.DIOLINO@GMAIL.COM"
    },
    {
        "NOME": "ANTONIO FRANCISCO FEITOSA SOUSA",
        "CLUBE": "MENSAGEIROS DA FÉ",
        "IGREJA": "SANTA GERTRUDES",
        "DISTRITO": "CERVEZON",
        "DATA DE NASCIMENTO": "1984-09-19",
        "CELULAR": "19987522761",
        "E-MAIL": "ANTONIO-FSA@OUTLOOK.COM"
    },
    {
        "NOME": "WALLACE JUNIO DA SILVEIRA BARBOSA",
        "CLUBE": "MENSAGEIROS DO UNIVERSO",
        "IGREJA": "CIDADE UNIVERSITÁRIA/E. COELHO",
        "DISTRITO": "CIDADE UNIVERSITÁRIA",
        "DATA DE NASCIMENTO": "1999-07-25",
        "CELULAR": "19999704275",
        "E-MAIL": "WALLACEBARBOSA99@GMAIL.COM"
    },
    {
        "NOME": "SILVIO DOBELIN",
        "CLUBE": "BENJAMIM",
        "IGREJA": "ENG. COELHO/EXTENSÃO UNIVERSITARIA",
        "DISTRITO": "CIDADE UNIVERSITÁRIA",
        "DATA DE NASCIMENTO": "1971-09-18",
        "CELULAR": "19996097420",
        "E-MAIL": "SILLVIO.DOBELIN@UNASP.EDU.BR"
    },
    {
        "NOME": "ELLIS SPINDOLA LUDTKE",
        "CLUBE": "GIGANTES DO VALE",
        "IGREJA": "JD. NOVO HORIZONTE",
        "DISTRITO": "CIDADE UNIVERSITÁRIA",
        "DATA DE NASCIMENTO": "1998-05-09",
        "CELULAR": "(73) 81058914",
        "E-MAIL": "ELLISLUDTKE@HOTMAIL.COM"
    },
    {
        "NOME": "VINICIUS QUIRINO DOS SANTOS",
        "CLUBE": "ELEMENTAIS",
        "IGREJA": "CAC",
        "DISTRITO": "COLEGIO ADVENTISTA CAMPINAS",
        "DATA DE NASCIMENTO": "1982-04-02",
        "CELULAR": "19.992.275.525",
        "E-MAIL": "ARDUINOSANTOS@GMAIL.COM"
    },
    {
        "NOME": "LUIZ ANTONIO CHAVES",
        "CLUBE": "ÁGAPE",
        "IGREJA": "JD. ESPERANÇA III",
        "DISTRITO": "CONCHAL",
        "DATA DE NASCIMENTO": "1955-06-12",
        "CELULAR": "(19)99580-1775",
        "E-MAIL": "LUIZCHAVES1312@GMAIL.COM"
    },
    {
        "NOME": "WILIAN LOBATO MODRO",
        "CLUBE": "LOBO GUARÁ",
        "IGREJA": "JD. PLANALTO",
        "DISTRITO": "CONCHAL",
        "DATA DE NASCIMENTO": "1971-05-11",
        "CELULAR": "(19)99629-3466",
        "E-MAIL": "WILIANLMODRO@GMAIL.COM"
    },
    {
        "NOME": "VÂNIA BURGOS DE JESUS",
        "CLUBE": "LUZ DO UNIVERSO",
        "IGREJA": "B. CIDADE ALTA",
        "DISTRITO": "COSMOPOLIS",
        "DATA DE NASCIMENTO": "1981-09-28",
        "CELULAR": "(19) 9863-1118",
        "E-MAIL": "CLUBELUZDOUNIVERSO@GMAIL.COM"
    },
    {
        "NOME": "ROSEANE MEIRELES DO NASCIMENTO",
        "CLUBE": "EXÉRCITO REAL",
        "IGREJA": "PQ. ESTER",
        "DISTRITO": "COSMOPOLIS",
        "DATA DE NASCIMENTO": "1988-08-26",
        "CELULAR": "(19) 99954-7281",
        "E-MAIL": "ANNYEMEISSAN17@GMAIL.COM"
    },
    {
        "NOME": "PAULO DE AZEVEDO BALERO",
        "CLUBE": "PEDRA BRANCA",
        "IGREJA": "DOIS CORREGOS",
        "DISTRITO": "DOIS CÓRREGOS",
        "DATA DE NASCIMENTO": "1986-03-13",
        "CELULAR": "(14) 991714569",
        "E-MAIL": "PAULOCOBAYACHE@HOTMAIL.COM"
    },
    {
        "NOME": "LUIS FERNANDO DOS SANTOS",
        "CLUBE": "TRIBOS",
        "IGREJA": "IGARAÇU DO TIETÊ",
        "DISTRITO": "DOIS CÓRREGOS",
        "DATA DE NASCIMENTO": "1986-03-04",
        "CELULAR": "14 98131 7056",
        "E-MAIL": "LUISFS75@YAHOO.COM.BR"
    },
    {
        "NOME": "JAQUELINE LEOPOLDINO DA SILVA",
        "CLUBE": "FAROL DA TORRE",
        "IGREJA": "TORRINHA",
        "DISTRITO": "DOIS CÓRREGOS",
        "DATA DE NASCIMENTO": "",
        "CELULAR": "",
        "E-MAIL": "JAQUELINE@GMAIL.COM"
    },
    {
        "NOME": "JULIO DA SILVA SANTOS",
        "CLUBE": "GUAIQUICA",
        "IGREJA": "JD. DO SOL",
        "DISTRITO": "ENGENHEIRO COELHO",
        "DATA DE NASCIMENTO": "1988-05-30",
        "CELULAR": "11 98204-9152",
        "E-MAIL": "JULIOSS88@HOTMAIL.COM"
    },
    {
        "NOME": "PAULO HENRIQUE FERNANDES COSTA",
        "CLUBE": "JASPE",
        "IGREJA": "JD. SÃO PAULO",
        "DISTRITO": "ENGENHEIRO COELHO",
        "DATA DE NASCIMENTO": "2002-04-14",
        "CELULAR": "19.988.436.222",
        "E-MAIL": "PAULOPHFCOSTA@GMAIL.COM"
    },
    {
        "NOME": "ANGELA ARAGOSO SILVESTRE E SILVA",
        "CLUBE": "FERAS",
        "IGREJA": "B. SAO FRANCISCO/ITATIBA",
        "DISTRITO": "ITATIBA",
        "DATA DE NASCIMENTO": "1972-09-06",
        "CELULAR": "(11) 964409850",
        "E-MAIL": "ANGELA.ARAGOSO@HOTMAIL.COM"
    },
    {
        "NOME": "ADRIANA DE OLIVEIRA SANTOS",
        "CLUBE": "ITALERTA",
        "IGREJA": "ITATIBA CENTRAL",
        "DISTRITO": "ITATIBA",
        "DATA DE NASCIMENTO": "1979-12-20",
        "CELULAR": "011942951564",
        "E-MAIL": "ADRIANAOLIVSAN201279@GMAIL.COM.COM"
    },
    {
        "NOME": "JANETE MOREIRA DO  NASCIMENTO",
        "CLUBE": "MENSAGEIROS DA COLINA",
        "IGREJA": "JD. DAS NAÇÕES",
        "DISTRITO": "ITATIBA",
        "DATA DE NASCIMENTO": "1973-02-10",
        "CELULAR": "011972635523",
        "E-MAIL": "JANETE.MNASCIMENTO@HOTMAIL.COM"
    },
    {
        "NOME": "NATANAEL SANTOS",
        "CLUBE": "PIONEIROS DE TUIUTI",
        "IGREJA": "TUIUTI",
        "DISTRITO": "ITATIBA",
        "DATA DE NASCIMENTO": "1994-10-04",
        "CELULAR": "11942520833",
        "E-MAIL": "NATANAELBODINHO@GMAIL.COM"
    },
    {
        "NOME": "ANDERSON DE SOUZA AMARO",
        "CLUBE": "FERAS DA NATUREZA",
        "IGREJA": "B. CRUZEIRO DO SUL",
        "DISTRITO": "JAGUARIÚNA",
        "DATA DE NASCIMENTO": "1998-05-22",
        "CELULAR": "19994684013",
        "E-MAIL": "DERAMARO10@GMAIL.COM"
    },
    {
        "NOME": "RENATA DA SILVA SANDES FERREIRA MEDEIROS",
        "CLUBE": "AVES DE RAPINA",
        "IGREJA": "B. FLORIANOPOLIS",
        "DISTRITO": "JAGUARIÚNA",
        "DATA DE NASCIMENTO": "2005-01-26",
        "CELULAR": "",
        "E-MAIL": "SANDESRENATA65@GMAIL.COM"
    },
    {
        "NOME": "JOÃO FREIRE MUNIZ JUNIOR",
        "CLUBE": "FAUNA",
        "IGREJA": "JAGUARIÚNA",
        "DISTRITO": "JAGUARIÚNA",
        "DATA DE NASCIMENTO": "1978-06-09",
        "CELULAR": "(19) 988938930",
        "E-MAIL": "JOAO.MUNIZ@HOTMAIL.COM.BR"
    },
    {
        "NOME": "GEORG WILSON FRANCZAK EBERT",
        "CLUBE": "KADOSH",
        "IGREJA": "JAU CENTRAL",
        "DISTRITO": "JAU",
        "DATA DE NASCIMENTO": "1987-12-26",
        "CELULAR": "41-998280258",
        "E-MAIL": "GDRTOLDOS@HOTMAIL.COM"
    },
    {
        "NOME": "JOÃO PEDRO DE CARVALHO DA COSTA",
        "CLUBE": "VALENTES DE DAVI",
        "IGREJA": "JD. AEROPORTO/CAMP.",
        "DISTRITO": "JD. AEROPORTO/CAMP.",
        "DATA DE NASCIMENTO": "2004-12-22",
        "CELULAR": "19982326520",
        "E-MAIL": "JP.PEDRO2212@GMAIL.COM"
    },
    {
        "NOME": "CLAUDETE DE MELO AIRES RODRIGUES",
        "CLUBE": "ÁGUIAS DO AMÉRICA",
        "IGREJA": "JD. NOVA AMÉRICA",
        "DISTRITO": "JD. AEROPORTO/CAMP.",
        "DATA DE NASCIMENTO": "1991-09-10",
        "CELULAR": "19999679669",
        "E-MAIL": "CLAUDETE@GMAIL.COM"
    },
    {
        "NOME": "WILSTER LUIS DA SILVA",
        "CLUBE": "ESQUADRÃO DA FÉ",
        "IGREJA": "JD. SANTO ANTONIO",
        "DISTRITO": "JD. AEROPORTO/CAMP.",
        "DATA DE NASCIMENTO": "1986-12-31",
        "CELULAR": "19.987.073.429",
        "E-MAIL": "WILSTER.LUIS45@GMAIL.COM"
    },
    {
        "NOME": "EMELLY DA SILVA",
        "CLUBE": "SENTINELAS DE ÓRION",
        "IGREJA": "JD. SÃO PEDRO",
        "DISTRITO": "JD. AEROPORTO/CAMP.",
        "DATA DE NASCIMENTO": "2003-08-13",
        "CELULAR": "19.989.061.909",
        "E-MAIL": "CAMARGOEMELLY8@GMAIL.COM"
    },
    {
        "NOME": "FELIPE CARLOS SILVA HERRERA",
        "CLUBE": "GUERREIROS DO VALE",
        "IGREJA": "PQ. UNIVERSITARIO",
        "DISTRITO": "JD. AEROPORTO/CAMP.",
        "DATA DE NASCIMENTO": "1999-10-11",
        "CELULAR": "988583556",
        "E-MAIL": "FELIPEHERRERA_99@HOTMAIL.COM"
    },
    {
        "NOME": "FABIO RAFAEL FELIX DA SILVA",
        "CLUBE": "SOLDADOS DE CANAÃ",
        "IGREJA": "VILA VITÓRIA 1",
        "DISTRITO": "JD. AEROPORTO/CAMP.",
        "DATA DE NASCIMENTO": "1988-11-24",
        "CELULAR": "992018152",
        "E-MAIL": "FABIORAFAEL.FELIX@HOTMAIL.COM"
    },
    {
        "NOME": "DAINYE SAFIRA PIMENTEL",
        "CLUBE": "ÁGUIAS DO BOA VISTA",
        "IGREJA": "JD. BOA VISTA",
        "DISTRITO": "JD. EULINA/CAMP.",
        "DATA DE NASCIMENTO": "",
        "CELULAR": "",
        "E-MAIL": "DAINYE@GMAIL.COM"
    },
    {
        "NOME": "FERNANDA SAMMARCO LANDIM",
        "CLUBE": "EXPLORADORES DE ÓRION",
        "IGREJA": "JD. EULINA",
        "DISTRITO": "JD. EULINA/CAMP.",
        "DATA DE NASCIMENTO": "1983-08-07",
        "CELULAR": "(19) 9989-08002",
        "E-MAIL": "FERNANDASAMMARCO@GMAIL.COM"
    },
    {
        "NOME": "GABRIEL FORNAZZARI",
        "CLUBE": "OREN",
        "IGREJA": "PQ. SANTA BARBARA",
        "DISTRITO": "JD. EULINA/CAMP.",
        "DATA DE NASCIMENTO": "1992-05-13",
        "CELULAR": "",
        "E-MAIL": "GABRIEL.FORNAZZARI@GMAIL.COM"
    },
    {
        "NOME": "LUIS FERNANDO ANKLAM",
        "CLUBE": "MENSAGEIROS DO FLAMBOYANT",
        "IGREJA": "JD. FLAMBOYANT",
        "DISTRITO": "JD. FLAMBOYANT",
        "DATA DE NASCIMENTO": "1977-06-24",
        "CELULAR": "1998147-8279",
        "E-MAIL": "LUIS.ANKLAM@GMAIL.COM"
    },
    {
        "NOME": "MARIA DA CONCEIÇÃO DA SILVA COSTA",
        "CLUBE": "ARAUTOS DO ADVENTO",
        "IGREJA": "JD. CAMPINA GRANDE",
        "DISTRITO": "JD. FLORENCE/CAMP.",
        "DATA DE NASCIMENTO": "1986-12-08",
        "CELULAR": "19987355927",
        "E-MAIL": "CONCEICAOCOSTA135@GMAIL.COM"
    },
    {
        "NOME": "GASPAR DOS REIS GABRIEL",
        "CLUBE": "PEDRA ANGULAR",
        "IGREJA": "JD. FLORENCE",
        "DISTRITO": "JD. FLORENCE/CAMP.",
        "DATA DE NASCIMENTO": "1972-11-26",
        "CELULAR": "19992396422",
        "E-MAIL": "GASPARGABRIELMADU@GMAIL.COM"
    },
    {
        "NOME": "LUIZ FRANCISCO RIZZI",
        "CLUBE": "FALCÃO REAL",
        "IGREJA": "JD. METONOPOLIS",
        "DISTRITO": "JD. FLORENCE/CAMP.",
        "DATA DE NASCIMENTO": "1979-06-27",
        "CELULAR": "19988863771",
        "E-MAIL": "FRANRIZZI1979@GMAIL.COM"
    },
    {
        "NOME": "GELSON GONÇALVES DOS SANTOS",
        "CLUBE": "CRÔNICAS",
        "IGREJA": "PQ. SÃO BENTO",
        "DISTRITO": "JD. FLORENCE/CAMP.",
        "DATA DE NASCIMENTO": "1964-10-10",
        "CELULAR": "19996413972",
        "E-MAIL": "GELSON.SANTOS1964@GMAIL.COM"
    },
    {
        "NOME": "ALEXANDRE FERREIRA ALVES",
        "CLUBE": "LEÃO DE JUDÁ",
        "IGREJA": "JD. GLEBA B",
        "DISTRITO": "JD. INDIANÓPOLIS",
        "DATA DE NASCIMENTO": "2002-02-26",
        "CELULAR": "19981649297",
        "E-MAIL": "ALEXANDRE30141860984401390@GMAIL.COM"
    },
    {
        "NOME": "ANALIA NOGUEIRA CARDOSO",
        "CLUBE": "EBENEZER",
        "IGREJA": "JD. ICARAI",
        "DISTRITO": "JD. INDIANÓPOLIS",
        "DATA DE NASCIMENTO": "1974-01-19",
        "CELULAR": "(19)994073617",
        "E-MAIL": "ANALIA.NOGUEIRA@YAHOO.COM.BR"
    },
    {
        "NOME": "MARIA APARECIDA DO NASCIMENTO NAVES",
        "CLUBE": "ÔMEGA",
        "IGREJA": "JD. INDIANOPOLIS",
        "DISTRITO": "JD. INDIANÓPOLIS",
        "DATA DE NASCIMENTO": "1965-01-21",
        "CELULAR": "17992763902",
        "E-MAIL": "CIDINHADESBRAVA@GMAIL.COM"
    },
    {
        "NOME": "LUCIANA DE JESUS OLIVEIRA",
        "CLUBE": "FALCÕES DO REI",
        "IGREJA": "JD. TELESP",
        "DISTRITO": "JD. INDIANÓPOLIS",
        "DATA DE NASCIMENTO": "1983-02-23",
        "CELULAR": "19984222619",
        "E-MAIL": "LUCIANADEJSS@HOTMAIL.COM"
    },
    {
        "NOME": "PALOMA SILVA GONÇALVES",
        "CLUBE": "PIONEIROS DO ADVENTO",
        "IGREJA": "JD. TELESP",
        "DISTRITO": "JD. INDIANÓPOLIS",
        "DATA DE NASCIMENTO": "1988-05-04",
        "CELULAR": "(19) 99112-1808",
        "E-MAIL": "LARALLANA24@GMAIL.COM"
    },
    {
        "NOME": "DIEGO FELIPE SILVA CAVALCANTE",
        "CLUBE": "SENTINELAS DA COLINA",
        "IGREJA": "CIDADE SATÉLITE IRIS 3",
        "DISTRITO": "JD. LONDRES/CAMP.",
        "DATA DE NASCIMENTO": "1991-10-12",
        "CELULAR": "19982189308",
        "E-MAIL": "PSIC.DIEGOCAVALCANTE@GMAIL.COM"
    },
    {
        "NOME": "RAYSSA FISCHER RENZO HENRIQUES",
        "CLUBE": "ALFA",
        "IGREJA": "JD. LONDRES",
        "DISTRITO": "JD. LONDRES/CAMP.",
        "DATA DE NASCIMENTO": "2006-04-04",
        "CELULAR": "19998668053",
        "E-MAIL": "RAYSSAFISCHER9@GMAIL.COM"
    },
    {
        "NOME": "JONIFER BELARMINO OLIVEIRA DOS SANTOS",
        "CLUBE": "MAKARIOS",
        "IGREJA": "JD. URUGUAI",
        "DISTRITO": "JD. LONDRES/CAMP.",
        "DATA DE NASCIMENTO": "1987-05-06",
        "CELULAR": "19988528656",
        "E-MAIL": "JONIFER6587@HOTMAIL.COM"
    },
    {
        "NOME": "JURANDIR ALBERTO PEREIRA",
        "CLUBE": "CARLOS GOMES",
        "IGREJA": "JD. DALL`ORTO",
        "DISTRITO": "JD. MARIA ANTÔNIA",
        "DATA DE NASCIMENTO": "1971-02-11",
        "CELULAR": "19.988.584.372",
        "E-MAIL": "JURAB176@GMAIL.COM"
    },
    {
        "NOME": "UBIRACY JOÃO DE CASTRO FILHO",
        "CLUBE": "ARKEIROS DO REI",
        "IGREJA": "JD. DOS IPÊS/SUMARÉ",
        "DISTRITO": "JD. MARIA ANTÔNIA",
        "DATA DE NASCIMENTO": "1984-10-07",
        "CELULAR": "",
        "E-MAIL": "UBIREACY@GMAIL.COM"
    },
    {
        "NOME": "DIANA NASCENTE DE ASSIS",
        "CLUBE": "LÍRIOS DO VALE",
        "IGREJA": "JD. MARIA ANTONIA",
        "DISTRITO": "JD. MARIA ANTÔNIA",
        "DATA DE NASCIMENTO": "1986-04-17",
        "CELULAR": "19 9 9767-1426",
        "E-MAIL": "DIANANASCENTE@HOTMAIL.COM"
    },
    {
        "NOME": "STEPHANIE VIEIRA FERREIRA JACINTO",
        "CLUBE": "ELITE SUMARÉ",
        "IGREJA": "PQ. IDEAL",
        "DISTRITO": "JD. MARIA ANTÔNIA",
        "DATA DE NASCIMENTO": "1991-01-25",
        "CELULAR": "11983759634",
        "E-MAIL": "STEPHANIE_PANTERS@HOTMAIL.COM"
    },
    {
        "NOME": "CARLOS ANTÔNIO GOMES DA COSTA",
        "CLUBE": "IMPACTO SUMARÉ",
        "IGREJA": "PQ. RESID. SEVILHA",
        "DISTRITO": "JD. MARIA ANTÔNIA",
        "DATA DE NASCIMENTO": "1964-08-30",
        "CELULAR": "(19) 99120-7798",
        "E-MAIL": "CARLOS.A.GOMES@HOTMAIL.COM"
    },
    {
        "NOME": "ANDERSON DE SOUZA",
        "CLUBE": "PEDRA DE FOGO",
        "IGREJA": "B. PENHA DO RIO DO PEIXE/ITAPIRA",
        "DISTRITO": "JD. NOVO 2",
        "DATA DE NASCIMENTO": "1996-04-16",
        "CELULAR": "19999202666",
        "E-MAIL": "ANDINHO.FOTOGRAFIA@GMAIL.COM"
    },
    {
        "NOME": "DELMA DA SILVA MONASKI FERREIRA",
        "CLUBE": "ÁGUIA IMPERIAL",
        "IGREJA": "BARÃO DE ATALIBA NOGUEIRA",
        "DISTRITO": "JD. NOVO 2",
        "DATA DE NASCIMENTO": "1978-07-27",
        "CELULAR": "(19) 98346-4550",
        "E-MAIL": "DELMAMONASKI31@GMAIL.COM"
    },
    {
        "NOME": "MAYCON BUENO PECOLO",
        "CLUBE": "HOME ADVENTURE",
        "IGREJA": "HOME CHURCH",
        "DISTRITO": "JD. NOVO 2",
        "DATA DE NASCIMENTO": "1981-10-29",
        "CELULAR": "19981982997",
        "E-MAIL": "MAYCON.PECOLO@GMAIL.COM"
    },
    {
        "NOME": "VICTOR FÉLIX DE LIMA",
        "CLUBE": "ÁGUIA NEGRA",
        "IGREJA": "JD. NOVO CAMPOS ELISEOS",
        "DISTRITO": "JD. NOVO CAMPOS ELISEOS / CAMP.",
        "DATA DE NASCIMENTO": "1993-07-07",
        "CELULAR": "019997410279",
        "E-MAIL": "VFELIX.LIMA@YAHOO.COM"
    },
    {
        "NOME": "SILVANA APARECIDA VIERA EUGENIO",
        "CLUBE": "ARCA DA FÉ",
        "IGREJA": "JD. SANTA LUCIA",
        "DISTRITO": "JD. NOVO CAMPOS ELISEOS / CAMP.",
        "DATA DE NASCIMENTO": "1982-08-19",
        "CELULAR": "019994475235",
        "E-MAIL": "SIL.EUGENIO@HOTMAIL.COM"
    },
    {
        "NOME": "ALINE CASTILHO FERREIRA",
        "CLUBE": "LOBOS DO PLANALTO",
        "IGREJA": "AGUAI",
        "DISTRITO": "JD. PROGRESSO",
        "DATA DE NASCIMENTO": "1987-05-04",
        "CELULAR": "19 98911 2336",
        "E-MAIL": "ALININHACASTILHOFERREIRA@GMAIL.COM"
    },
    {
        "NOME": "SAMUEL GONÇALVES DA SILVA",
        "CLUBE": "FALCÕES DA MANTIQUEIRA",
        "IGREJA": "JD. PROGRESSO",
        "DISTRITO": "JD. PROGRESSO",
        "DATA DE NASCIMENTO": "2001-10-20",
        "CELULAR": "19991168620",
        "E-MAIL": "SAMUELGONSILVA009@GMAIL.COM"
    },
    {
        "NOME": "SANDRA APARECIDA RIBEIRO DA SILVA",
        "CLUBE": "LUZEIROS DA SERRA",
        "IGREJA": "JD. VARAM",
        "DISTRITO": "JD. PROGRESSO",
        "DATA DE NASCIMENTO": "1973-07-25",
        "CELULAR": "19994579478",
        "E-MAIL": "SANDRAAPARECIDARBR43@GMAIL.COM"
    },
    {
        "NOME": "ABNER LUCAS DE OLIVEIRA LEITE",
        "CLUBE": "PYXIS",
        "IGREJA": "B. BOM SUCESSO/CAMPINAS",
        "DISTRITO": "JD. SAMAMBAIA",
        "DATA DE NASCIMENTO": "1993-07-07",
        "CELULAR": "992622254",
        "E-MAIL": "ABNERLEITE7@GMAIL.COM"
    },
    {
        "NOME": "VICENTE PEREIRA DE DEUS",
        "CLUBE": "ANTARES",
        "IGREJA": "JD. BARONEZA",
        "DISTRITO": "JD. SAMAMBAIA",
        "DATA DE NASCIMENTO": "1949-11-26",
        "CELULAR": "19-99930-8733",
        "E-MAIL": "TIAKROL2@GMAIL.COM"
    },
    {
        "NOME": "PAMELA BEATRIZ DOS REIS GARCIA",
        "CLUBE": "VIDEIRA",
        "IGREJA": "JD. DOS ANDORINHAS",
        "DISTRITO": "JD. SAMAMBAIA",
        "DATA DE NASCIMENTO": "2000-09-23",
        "CELULAR": "(19) 98769-6575",
        "E-MAIL": "PAMELAREIS.GARCIA@GMAIL.COM"
    },
    {
        "NOME": "MARA CRISTINA APARECIDA MARTINS BENTO CARDAMONI",
        "CLUBE": "MONTE DOS OLIVEIRAS",
        "IGREJA": "JD. DOS OLIVEIRAS",
        "DISTRITO": "JD. SAMAMBAIA",
        "DATA DE NASCIMENTO": "1981-08-11",
        "CELULAR": "19992209754",
        "E-MAIL": "MARACARDAMONI@HOTMAIL.COM"
    },
    {
        "NOME": "EDILAINE DA ROSA DIAS",
        "CLUBE": "CHAZAK",
        "IGREJA": "JD. SAMAMBAIA",
        "DISTRITO": "JD. SAMAMBAIA",
        "DATA DE NASCIMENTO": "1991-04-29",
        "CELULAR": "19999298428",
        "E-MAIL": "EDILAINEDAROSA@GMAIL.COM"
    },
    {
        "NOME": "LUCAS ELIAS DA SILVA",
        "CLUBE": "LEÕES DA COLINA",
        "IGREJA": "CASA BRANCA",
        "DISTRITO": "JD. SÃO PEDRO",
        "DATA DE NASCIMENTO": "1981-01-11",
        "CELULAR": "19995531963",
        "E-MAIL": "LUCASELIASDAS@GMAIL.COM"
    },
    {
        "NOME": "ADAILSON PEREIRA DE OLIVEIRA",
        "CLUBE": "PIONEIROS DO RIO VERDE",
        "IGREJA": "ITOBI",
        "DISTRITO": "JD. SÃO PEDRO",
        "DATA DE NASCIMENTO": "1981-01-27",
        "CELULAR": "19 99868-8823",
        "E-MAIL": "ADAILSON@GMAIL.COM"
    },
    {
        "NOME": "MADALENA APARECIDA DOS SANTOS OLIVA",
        "CLUBE": "ESTRELA POLAR",
        "IGREJA": "SANTA CRUZ DAS PALMEIRAS",
        "DISTRITO": "JD. SÃO PEDRO",
        "DATA DE NASCIMENTO": "1970-04-29",
        "CELULAR": "19.981.773.584",
        "E-MAIL": "MADA.OLIVA@HOTMAIL.COM"
    },
    {
        "NOME": "JULIANA DA SILVA TEIXEIRA",
        "CLUBE": "VIGILANTES DO CERRADO",
        "IGREJA": "VILA SANTA FE",
        "DISTRITO": "JD. SÃO PEDRO",
        "DATA DE NASCIMENTO": "2003-05-27",
        "CELULAR": "19999483461",
        "E-MAIL": "JULIANA.LOPES133@HOTMAIL.COM"
    },
    {
        "NOME": "MATHEUS DA SILVA SANTOS",
        "CLUBE": "KAIRÓS",
        "IGREJA": "ESPAÇO NOVO TEMPO - ELOY CHAVES",
        "DISTRITO": "JUNDIAI CENTRAL",
        "DATA DE NASCIMENTO": "1998-04-22",
        "CELULAR": "(13)997907832",
        "E-MAIL": "MATHEUSJOVENAGRICULTOR@GMAIL.COM"
    },
    {
        "NOME": "SIMONE NARCISO ROSA POLL",
        "CLUBE": "CONEXÃO JAPI",
        "IGREJA": "JUNDIAI CENTRAL",
        "DISTRITO": "JUNDIAI CENTRAL",
        "DATA DE NASCIMENTO": "1979-05-27",
        "CELULAR": "(11) 9943-76811",
        "E-MAIL": "SIMONEROSA.POLL@GMAIL.COM"
    },
    {
        "NOME": "ANDRÉA DE FREITAS CARDOSO DOS SANTOS",
        "CLUBE": "GUARDIÕES DO FLORESTAL",
        "IGREJA": "JUNDIAI CENTRAL",
        "DISTRITO": "JUNDIAI CENTRAL",
        "DATA DE NASCIMENTO": "1980-02-17",
        "CELULAR": "11981510764",
        "E-MAIL": "ANDREA.FCARDOSO@HOTMAIL.COM"
    },
    {
        "NOME": "CINTIA MARIA SILVA DE OLIVEIRA",
        "CLUBE": "GUARDIÕES DA GALAXIA",
        "IGREJA": "JD. DAS PALMEIRAS",
        "DISTRITO": "LEME",
        "DATA DE NASCIMENTO": "1990-11-27",
        "CELULAR": "",
        "E-MAIL": "MCINTIA19@GMAIL.COM"
    },
    {
        "NOME": "ANDRÉ DE LIMA GROSSKLAUSS",
        "CLUBE": "CAPITÃO DO VALE",
        "IGREJA": "JD. LIVIA",
        "DISTRITO": "LEME",
        "DATA DE NASCIMENTO": "1986-06-23",
        "CELULAR": "996201271",
        "E-MAIL": "ANDREGROSSK@GMAIL.COM"
    },
    {
        "NOME": "ELIANE FERNANDA DOS SANTOS DINIZ SOBRAL",
        "CLUBE": "ATALAIAS DA COLINA",
        "IGREJA": "LEME CENTRAL",
        "DISTRITO": "LEME",
        "DATA DE NASCIMENTO": "1987-10-08",
        "CELULAR": "(19) 9835-06699",
        "E-MAIL": "THSOBRAL@HOTMAIL.COM"
    },
    {
        "NOME": "VANESSA PROFERI MARQUETTI DENDENA",
        "CLUBE": "SENHOR DAS ÁGUIAS",
        "IGREJA": "MOCOCA CENTRAL",
        "DISTRITO": "MOCOCA",
        "DATA DE NASCIMENTO": "1993-02-18",
        "CELULAR": "(19)98949-8956",
        "E-MAIL": "NESSAMARQUETTI@GMAIL.COM"
    },
    {
        "NOME": "TIAGO DA COSTA PINTO",
        "CLUBE": "CRUX",
        "IGREJA": "SAO JOSE DO RIO PARDO",
        "DISTRITO": "MOCOCA",
        "DATA DE NASCIMENTO": "1989-02-27",
        "CELULAR": "(19) 9337-3818",
        "E-MAIL": "TI_DACOSTA@HOTMAIL.COM"
    },
    {
        "NOME": "RENAN PRADO RODRIGUES",
        "CLUBE": "VALE DO GUAÇU",
        "IGREJA": "ESPAÇO NOVO TEMPO",
        "DISTRITO": "MOGI GUAÇU",
        "DATA DE NASCIMENTO": "1987-04-23",
        "CELULAR": "19.993.843.783",
        "E-MAIL": "EUMEMO.RODRIGUES@HOTMAIL.COM"
    },
    {
        "NOME": "GABRIEL DE SOUZA CAMARGO",
        "CLUBE": "YPÊ CELESTE",
        "IGREJA": "JD. GUAÇUANO",
        "DISTRITO": "MOGI GUAÇU",
        "DATA DE NASCIMENTO": "2003-02-17",
        "CELULAR": "(19) 984423898",
        "E-MAIL": "GABAZERASOUZA@GMAIL.COM"
    },
    {
        "NOME": "IVANNA EVELLYN DE OLIVEIRA SOUZA",
        "CLUBE": "ATLÂNTICO",
        "IGREJA": "JD. SAO PEDRO/MOGI GUACU",
        "DISTRITO": "MOGI GUAÇU",
        "DATA DE NASCIMENTO": "1997-06-12",
        "CELULAR": "(81)98416-0073",
        "E-MAIL": "IVANNAEVELLYN18@HOTMAIL.COM"
    },
    {
        "NOME": "SARA  DE OLIVEIRA RODRIGUES",
        "CLUBE": "NOVE DE ABRIL",
        "IGREJA": "MOGI GUAÇU CENTRAL",
        "DISTRITO": "MOGI GUAÇU",
        "DATA DE NASCIMENTO": "1987-11-20",
        "CELULAR": "(19) 987488886",
        "E-MAIL": "SARINHACASTIGLIONI@GMAIL.COM"
    },
    {
        "NOME": "VICTOR HUGO DE VASCONCELOS",
        "CLUBE": "RIO DO VALE",
        "IGREJA": "PQ. CIDADE NOVA/MOGI GUAÇU",
        "DISTRITO": "MOGI GUAÇU",
        "DATA DE NASCIMENTO": "1996-06-18",
        "CELULAR": "(19)981402270",
        "E-MAIL": "VICTORHG.VASCONCELOS@GMAIL.COM"
    },
    {
        "NOME": "EVELIN ROSA RODRIGUES",
        "CLUBE": "SAVANA",
        "IGREJA": "JD. MARIA BEATRIZ",
        "DISTRITO": "MOGI MIRIM",
        "DATA DE NASCIMENTO": "1988-06-17",
        "CELULAR": "19 99645-6118",
        "E-MAIL": "EBELINHA@HOTMAIL.COM"
    },
    {
        "NOME": "MARTA DA SILVA CONSTANTINO",
        "CLUBE": "GIGANTES DE MOGI",
        "IGREJA": "JD. SILVANIA",
        "DISTRITO": "MOGI MIRIM",
        "DATA DE NASCIMENTO": "1967-09-08",
        "CELULAR": "(19) 9654-2960",
        "E-MAIL": "MARTA.CONSTANTINO67@GMAIL.COM"
    },
    {
        "NOME": "ROBISON DOS ANJOS TRAVA",
        "CLUBE": "EVEREST",
        "IGREJA": "MOGI MIRIM CENTRAL",
        "DISTRITO": "MOGI MIRIM",
        "DATA DE NASCIMENTO": "1990-02-07",
        "CELULAR": "19 98921-4802",
        "E-MAIL": "ROBISONTRAVA@HOTMAIL.COM"
    },
    {
        "NOME": "PAULO FRANCELINO DE OLIVEIRA",
        "CLUBE": "PIONEIROS DE MOGI MIRIM",
        "IGREJA": "PQ. DAS LARANJEIRAS",
        "DISTRITO": "MOGI MIRIM",
        "DATA DE NASCIMENTO": "1965-11-04",
        "CELULAR": "(99) 26007-48",
        "E-MAIL": "FRANCELINODE@GMAIL.COM"
    },
    {
        "NOME": "ROSÃNGELA MARIA TEODORO MANÊRA",
        "CLUBE": "ESTRELA DA MANHÃ",
        "IGREJA": "VILA DIAS",
        "DISTRITO": "MOGI MIRIM",
        "DATA DE NASCIMENTO": "1970-10-09",
        "CELULAR": "19-989428835",
        "E-MAIL": "ROSANGELATEODOROMANERA@GMAIL.COM"
    },
    {
        "NOME": "JHENIFER APARECIDA MIRANDA DE SOUZA SILVA",
        "CLUBE": "GUERREIROS DE CRISTO",
        "IGREJA": "B. JOAO ARANHA/PAULINIA",
        "DISTRITO": "PAULÍNIA",
        "DATA DE NASCIMENTO": "1998-10-12",
        "CELULAR": "19983953803",
        "E-MAIL": "JHENYFFER_MS1@HOTMAIL.COM"
    },
    {
        "NOME": "ROSELI APARECIDA THOMÉ",
        "CLUBE": "GUERREIROS DA FÉ",
        "IGREJA": "B. SÃO JOSÉ/PAULÍNIA",
        "DISTRITO": "PAULÍNIA",
        "DATA DE NASCIMENTO": "1980-02-08",
        "CELULAR": "19974087931",
        "E-MAIL": "ROSENOVAAISS@GMAIL.COM"
    },
    {
        "NOME": "MARLUCE DE SOUSA FERREIRA DIAS",
        "CLUBE": "SÍRIUS",
        "IGREJA": "BOM RETIRO/PAULINIA",
        "DISTRITO": "PAULÍNIA",
        "DATA DE NASCIMENTO": "1974-01-28",
        "CELULAR": "19 98280-4959",
        "E-MAIL": "MARLUCE@GMAIL.COM"
    },
    {
        "NOME": "CHARLENE KETLY MARTINS DA SILVA ARAUJO",
        "CLUBE": "VALENTES DE PAULINIA",
        "IGREJA": "C.A PAULINIA",
        "DISTRITO": "PAULÍNIA",
        "DATA DE NASCIMENTO": "1981-11-06",
        "CELULAR": "19991358575",
        "E-MAIL": "CHARLENEKETLY@GMAIL.COM"
    },
    {
        "NOME": "ELDO EZEQUIEL MARTINS",
        "CLUBE": "SHALOM",
        "IGREJA": "PAULINIA",
        "DISTRITO": "PAULÍNIA",
        "DATA DE NASCIMENTO": "1953-08-17",
        "CELULAR": "(11) 984926222",
        "E-MAIL": "ELDO.MAR@TERRA.COM.BR"
    },
    {
        "NOME": "SIMONE SANTOS DA HORA DE OLIVEIRA",
        "CLUBE": "SERRA AZUL",
        "IGREJA": "SERRA AZUL",
        "DISTRITO": "PAULÍNIA",
        "DATA DE NASCIMENTO": "1977-12-23",
        "CELULAR": "(19) 987207157",
        "E-MAIL": "SAMUELROLIVER10@GMAIL.COM"
    },
    {
        "NOME": "MARCELO OZONO MARTINEZ",
        "CLUBE": "SENTINELAS DE AMPARO",
        "IGREJA": "AMPARO",
        "DISTRITO": "PEDREIRA",
        "DATA DE NASCIMENTO": "1978-03-03",
        "CELULAR": "(11) 98594-2853",
        "E-MAIL": "DIRETORIA@SENTINELASDEAMPARO.ORG.BR"
    },
    {
        "NOME": "Lavinia Araujo Gonçalves Rodrigues",
        "CLUBE": "Guardiões da Figueira",
        "IGREJA": "Santo Antônio",
        "DISTRITO": "São João da Boa Vista",
        "DATA DE NASCIMENTO": "15/03/2025",
        "CELULAR": "19991889112",
        "E-MAIL": "lavinia.rodrigues@sou.unifeob.edu.br"
    },
    {
        "NOME": "MARCELO MATINEZ",
        "CLUBE": "SENTINELAS DO LAGO",
        "IGREJA": "ARTUR NOUGUEIRA",
        "DISTRITO": "ARTUR NOUGUEIRA",
        "DATA DE NASCIMENTO": "2025-04-16",
        "CELULAR": "(11) 98594-2853",
        "E-MAIL": ""
    },
    {
        "NOME": "FRANCISCO RODRIGUES DA SILVA",
        "CLUBE": "ÁGUIAS DO EVEREST",
        "IGREJA": "JD. MARAJOARA",
        "DISTRITO": "PEDREIRA",
        "DATA DE NASCIMENTO": "1988-07-28",
        "CELULAR": "19999616903",
        "E-MAIL": "MARANHAO2807@GMAIL.COM"
    },
    {
        "NOME": "BRUNO DE OLIVEIRA CONCEIÇÃO",
        "CLUBE": "CORDEIROS DO MONTE",
        "IGREJA": "MONTE ALEGRE DO SUL",
        "DISTRITO": "PEDREIRA",
        "DATA DE NASCIMENTO": "1996-07-30",
        "CELULAR": "19.997.931.604",
        "E-MAIL": "BRUNO@GMAIL.COM"
    },
    {
        "NOME": "MATHEUS EDUARDO GARCIA MARQUES",
        "CLUBE": "JOHN HANCOCK",
        "IGREJA": "PIRASSUNUNGA CENTRAL",
        "DISTRITO": "PIRASSUNUNGA",
        "DATA DE NASCIMENTO": "2006-04-15",
        "CELULAR": "(19) 99850-7270",
        "E-MAIL": "MATHEUS.091228@GMAIL.COM"
    },
    {
        "NOME": "MARCOS RODRIGUES FORTUNATO",
        "CLUBE": "HENRY BERG",
        "IGREJA": "PQ. CRISTO REDENTOR/P.FERREIRA",
        "DISTRITO": "PIRASSUNUNGA",
        "DATA DE NASCIMENTO": "1979-05-25",
        "CELULAR": "",
        "E-MAIL": "MARCOS@GMAIL.COM"
    },
    {
        "NOME": "JOÃO PAULO FERREIRA DIAS",
        "CLUBE": "LUZEIROS DO NORTE",
        "IGREJA": "ZONA NORTE",
        "DISTRITO": "PIRASSUNUNGA",
        "DATA DE NASCIMENTO": "1985-12-24",
        "CELULAR": "(19)997613537",
        "E-MAIL": "GRAXA_VSP@HOTMAIL.COM"
    },
    {
        "NOME": "ARTHUR FRANCHESCO GOMES DOS SANTOS DE OLIVEIRA",
        "CLUBE": "ÁGUIA REAL",
        "IGREJA": "JD. BLUMENAU",
        "DISTRITO": "PQ. DAS FLORES",
        "DATA DE NASCIMENTO": "1998-11-25",
        "CELULAR": "(19) 9204-8276",
        "E-MAIL": "ARTUR@GMAIL.COM"
    },
    {
        "NOME": "MARIA DO ROSÁRIO F. CAJÁ",
        "CLUBE": "CONDOR",
        "IGREJA": "JD. PRIMAVERA/ARTUR N.",
        "DISTRITO": "PQ. DAS FLORES",
        "DATA DE NASCIMENTO": "1954-03-02",
        "CELULAR": "19997638380",
        "E-MAIL": "FUNILARIACAJA@GMAIL.COM"
    },
    {
        "NOME": "JULIANA XAVIER NEVES",
        "CLUBE": "SERVOS DO REI",
        "IGREJA": "JD. SACILOTTO II",
        "DISTRITO": "PQ. DAS FLORES",
        "DATA DE NASCIMENTO": "1989-02-03",
        "CELULAR": "(19) 992012839",
        "E-MAIL": "JULIANAJXN@GMAIL.COM"
    },
    {
        "NOME": "EZEQUIEL FAUSTINO ROCHA",
        "CLUBE": "FALCÃO",
        "IGREJA": "PQ. DAS FLORES",
        "DISTRITO": "PQ. DAS FLORES",
        "DATA DE NASCIMENTO": "1987-11-09",
        "CELULAR": "19989422350",
        "E-MAIL": "FAUSTINOROCHAEZEQUIEL@GMAIL.COM"
    },
    {
        "NOME": "GENILSON CRISPIM DA SILVA",
        "CLUBE": "GUARDIÕES DA ALVORADA",
        "IGREJA": "PQ. DAS FLORES",
        "DISTRITO": "PQ. DAS FLORES",
        "DATA DE NASCIMENTO": "1992-04-16",
        "CELULAR": "19.996.460.858",
        "E-MAIL": "GENILSON16.04@GMAIL.COM"
    },
    {
        "NOME": "EMILY MARIA HERGERT",
        "CLUBE": "NOGUEIRA REAL",
        "IGREJA": "PQ. DAS FLORES",
        "DISTRITO": "PQ. DAS FLORES",
        "DATA DE NASCIMENTO": "1989-05-08",
        "CELULAR": "(19)99965 7883",
        "E-MAIL": "EMILYHERGERT_@HOTMAIL.COM"
    },
    {
        "NOME": "RENAN ROBSON DE SOUZA",
        "CLUBE": "LEÕES DOS PINHEIROS",
        "IGREJA": "B. SÃO JOÃO DOS PINHEIROS",
        "DISTRITO": "PQ. DOS TRABALHADORES/ARTUR N.",
        "DATA DE NASCIMENTO": "1989-05-15",
        "CELULAR": "(19) 991834302",
        "E-MAIL": "RENANROBSONCAROLINA@GMAIL.COM"
    },
    {
        "NOME": "JOSE DOS REIS",
        "CLUBE": "LEÕES DO REI",
        "IGREJA": "VILLA MOLLON IV",
        "DISTRITO": "",
        "DATA DE NASCIMENTO": "",
        "CELULAR": "",
        "E-MAIL": "crisejunior_reis@hotmail.com"
    },
    {
        "NOME": "PEDRO GABRIEL DE SOUSA BUENO",
        "CLUBE": "VITÓRIA RÉGIA",
        "IGREJA": "HOLAMBRA",
        "DISTRITO": "PQ. DOS TRABALHADORES/ARTUR N.",
        "DATA DE NASCIMENTO": "1999-08-20",
        "CELULAR": "(19) 74201884",
        "E-MAIL": "BIELBUENO1999@HOTMAIL.COM"
    },
    {
        "NOME": "TIAGO DO NASCIMENTO",
        "CLUBE": "ALBATROZ",
        "IGREJA": "PQ. RESID. ITAMARATY",
        "DISTRITO": "PQ. DOS TRABALHADORES/ARTUR N.",
        "DATA DE NASCIMENTO": "1982-09-05",
        "CELULAR": "19998142256",
        "E-MAIL": "JAMESNASCWHITE@HOTMAIL.COM"
    },
    {
        "NOME": "MARCOS VINICIUS DA CRUZ MACHADO",
        "CLUBE": "GUARDIÕES DO JAPI",
        "IGREJA": "CABREUVA",
        "DISTRITO": "PQ. RESID. JUNDIAI",
        "DATA DE NASCIMENTO": "1984-01-11",
        "CELULAR": "(73) 98492830",
        "E-MAIL": "MARVINYUSS@GMAIL.COM"
    },
    {
        "NOME": "DANIEL COSTA LIMA",
        "CLUBE": "SAMIR",
        "IGREJA": "ITUPEVA",
        "DISTRITO": "PQ. RESID. JUNDIAI",
        "DATA DE NASCIMENTO": "1998-08-19",
        "CELULAR": "(11) 9958-94022",
        "E-MAIL": "DANIELTO400@GMAIL.COM"
    },
    {
        "NOME": "NELCI JOSÉ DA CRUZ",
        "CLUBE": "EXÉRCITO DE GIDEÃO",
        "IGREJA": "MONTE SERRAT",
        "DISTRITO": "PQ. RESID. JUNDIAI",
        "DATA DE NASCIMENTO": "1974-08-03",
        "CELULAR": "(11) 95814-6716",
        "E-MAIL": "NELCICJOSE@GMAIL.COM"
    },
    {
        "NOME": "CÍCERA MARIA DA SILVA DE MOURA",
        "CLUBE": "BERIT",
        "IGREJA": "PQ. RESID. JUNDIAI",
        "DISTRITO": "PQ. RESID. JUNDIAI",
        "DATA DE NASCIMENTO": "1970-06-27",
        "CELULAR": "11951592368",
        "E-MAIL": "CISA41@HOTMAIL.COM"
    },
    {
        "NOME": "LUCAS RODRIGUES MENDES",
        "CLUBE": "ESMERALDA",
        "IGREJA": "JD. ESMERALDA",
        "DISTRITO": "RIO CLARO",
        "DATA DE NASCIMENTO": "2000-07-21",
        "CELULAR": "19 97118-9497",
        "E-MAIL": "LR.MENDES@OUTLOOK.COM"
    },
    {
        "NOME": "JOHNNY FERNANDES MARIANO HENRIQUE",
        "CLUBE": "CIDADE AZUL",
        "IGREJA": "RIO CLARO CENTRAL",
        "DISTRITO": "RIO CLARO",
        "DATA DE NASCIMENTO": "1988-10-16",
        "CELULAR": "(19) 97642-676",
        "E-MAIL": "JOHNNYFHENRIQUE@HOTMAIL.COM"
    },
    {
        "NOME": "GUILHERME MARTINS DO CARMO NUNES",
        "CLUBE": "ÁGUIAS DO JARDIM",
        "IGREJA": "SANTO ANTONIO DO JARDIM",
        "DISTRITO": "SÃO JOÃO DA BOA VISTA",
        "DATA DE NASCIMENTO": "1994-11-21",
        "CELULAR": "(11) 993266733",
        "E-MAIL": "GMTS@HOTMAIL.COM.BR"
    },
    {
        "NOME": "ANA LÍDIA MENDES MESSIAS",
        "CLUBE": "SANTOS DUMONT",
        "IGREJA": "SAO JOAO DA BOA VISTA",
        "DISTRITO": "SÃO JOÃO DA BOA VISTA",
        "DATA DE NASCIMENTO": "1981-08-25",
        "CELULAR": "19999655289",
        "E-MAIL": "LOJAVENEIR@GMAIL.COM"
    },
    {
        "NOME": "LAURA GEOVANNA SASSERON",
        "CLUBE": "ÁGUIAS DA MANTIQUEIRA",
        "IGREJA": "VARGEM GRANDE DO SUL",
        "DISTRITO": "SÃO JOÃO DA BOA VISTA",
        "DATA DE NASCIMENTO": "1998-10-14",
        "CELULAR": "19 98442-2840",
        "E-MAIL": "GEOVANASASSERON-@HOTMAIL.COM"
    },
    {
        "NOME": "JOSÉLIA CHAVES RODRIGUES",
        "CLUBE": "GUARDIÕES DA ESPERANÇA",
        "IGREJA": "JD. ORQUIDEA",
        "DISTRITO": "SÃO JORGE",
        "DATA DE NASCIMENTO": "1985-09-26",
        "CELULAR": "19.997.608.973",
        "E-MAIL": "DESBRAVADORESGUARANCA@GMAIL.COM"
    },
    {
        "NOME": "YURI GUILHERME REZENDE",
        "CLUBE": "ÁGUIAS DA ESPERANÇA",
        "IGREJA": "JD. SAO MANOEL/NOVA ODESSA",
        "DISTRITO": "SÃO JORGE",
        "DATA DE NASCIMENTO": "2004-01-08",
        "CELULAR": "(19)993110277",
        "E-MAIL": "YUZENDE298@GMAIL.COM"
    },
    {
        "NOME": "JAIR ALVES DE OLIVEIRA JÚNIOR",
        "CLUBE": "GUARDIÕES DA ALIANÇA",
        "IGREJA": "SOCORRO CENTRAL",
        "DISTRITO": "SOCORRO",
        "DATA DE NASCIMENTO": "1991-03-27",
        "CELULAR": "(19) 9315-9452",
        "E-MAIL": "JAIROLIVEIRAJR77@GMAIL.COM"
    },
    {
        "NOME": "CLEITON DE MORAES",
        "CLUBE": "SHAMAH",
        "IGREJA": "SOCORRO CENTRAL",
        "DISTRITO": "SOCORRO",
        "DATA DE NASCIMENTO": "1984-08-09",
        "CELULAR": "(19)995651357",
        "E-MAIL": "TOMCLEITONMORAES7@GMAIL.COM"
    },
    {
        "NOME": "MARIA EMÍLIA SANTOS DE SOUZA",
        "CLUBE": "ROSA DE SARON",
        "IGREJA": "ALTOS DE SUMARE",
        "DISTRITO": "SUMARE CENTRAL",
        "DATA DE NASCIMENTO": "1999-09-17",
        "CELULAR": "",
        "E-MAIL": "MARIA@GMAIL.COM"
    },
    {
        "NOME": "MARIA CRISTINA PRASTELLI DO PRADO",
        "CLUBE": "BRILHO DE JASPE",
        "IGREJA": "JD. SANTA MADALENA",
        "DISTRITO": "SUMARE CENTRAL",
        "DATA DE NASCIMENTO": "1964-05-09",
        "CELULAR": "19974045148",
        "E-MAIL": "CRIS_PRADO2@HOTMAIL.COM"
    },
    {
        "NOME": "RAFAELA CRISTINA DA SILVA",
        "CLUBE": "ALPES CLUBE",
        "IGREJA": "SUMARE CENTRAL",
        "DISTRITO": "SUMARE CENTRAL",
        "DATA DE NASCIMENTO": "1989-06-08",
        "CELULAR": "1991461848",
        "E-MAIL": "RAFAELACSILVA07@HOTMAIL.COM"
    },
    {
        "NOME": "LUCAS MOREIRA DE ALMEIDA MENDES",
        "CLUBE": "ARCANJO",
        "IGREJA": "VILA MENUZO",
        "DISTRITO": "SUMARE CENTRAL",
        "DATA DE NASCIMENTO": "1995-01-31",
        "CELULAR": "(19) 9828-2114",
        "E-MAIL": "LUCAS@GMAIL.COM"
    },
    {
        "NOME": "WATSON DO NASCIMENTO COSTA",
        "CLUBE": "GUERREIROS DO ADVENTO",
        "IGREJA": "VILA SOMA",
        "DISTRITO": "SUMARE CENTRAL",
        "DATA DE NASCIMENTO": "1982-05-20",
        "CELULAR": "98987425780",
        "E-MAIL": "WATSONNCOSTA@GMAIL.COM"
    },
    {
        "NOME": "GISLAINE CRISTINA FOGUEL COELHO",
        "CLUBE": "FLAMBOYANT",
        "IGREJA": "UNASP-C2/E.COELHO",
        "DISTRITO": "UNASP-C2/E.COELHO",
        "DATA DE NASCIMENTO": "1979-05-25",
        "CELULAR": "19.999.410.534",
        "E-MAIL": "GISEZERO@GMAIL.COM"
    },
    {
        "NOME": "THIAGO GABRIEL DA SILVA PALMA LOPES",
        "CLUBE": "MINISTRY",
        "IGREJA": "UNASP-C2/E.COELHO",
        "DISTRITO": "UNASP-C2/E.COELHO",
        "DATA DE NASCIMENTO": "2000-01-03",
        "CELULAR": "(11) 98959-8418",
        "E-MAIL": "THIAGOLOPES1511@GMAIL.COM"
    },
    {
        "NOME": "LEANDRO DE SOUZA GONÇALVES",
        "CLUBE": "PIONEIROS DO VALE",
        "IGREJA": "JD. SÃO LUIZ",
        "DISTRITO": "VALINHOS",
        "DATA DE NASCIMENTO": "1986-04-13",
        "CELULAR": "11997572262",
        "E-MAIL": "LDO_SBC@HOTMAIL.COM"
    },
    {
        "NOME": "SUSAN MARÍA  GUERRERO RENTERIA",
        "CLUBE": "MENSAGEIROS DO REI",
        "IGREJA": "VALINHOS",
        "DISTRITO": "VALINHOS",
        "DATA DE NASCIMENTO": "1974-11-01",
        "CELULAR": "19.996.105.505",
        "E-MAIL": "SUSAN.GUERRERO@HOTMAIL.COM"
    },
    {
        "NOME": "MARIA VITÓRIA",
        "CLUBE": "MENSAGEIROS DO YEDA",
        "IGREJA": "YEDA",
        "DISTRITO": "YEDA",
        "DATA DE NASCIMENTO": "2025-11-01",
        "CELULAR": "",
        "E-MAIL": ""
    },
    {
        "NOME": "MARIA",
        "CLUBE": "TAURUS",
        "IGREJA": "FERNANDA",
        "DISTRITO": "CIDADE SINGER",
        "DATA DE NASCIMENTO": "1925-05-10",
        "CELULAR": "",
        "E-MAIL": ""
    },
    {
        "NOME": "NERISNETO CARVALHO DA SILVA",
        "CLUBE": "ADVENTO",
        "IGREJA": "JARINU",
        "DISTRITO": "VARZEA PAULISTA",
        "DATA DE NASCIMENTO": "1970-05-10",
        "CELULAR": "(11) 6451-2556",
        "E-MAIL": "NERISNETO@GMAIL.COM"
    },
    {
        "NOME": "MATHEUS TROMBINI PILLA",
        "CLUBE": "ÉZEN",
        "IGREJA": "VARZEA PAULISTA",
        "DISTRITO": "VARZEA PAULISTA",
        "DATA DE NASCIMENTO": "1993-04-26",
        "CELULAR": "(14) 98150-3049",
        "E-MAIL": "MATHEUS.TROMBINI@OUTLOOK.COM"
    },
    {
        "NOME": "CRISTINA DE JESUS BUBELA",
        "CLUBE": "GUERREIROS DO PLANALTO",
        "IGREJA": "BOCAINA",
        "DISTRITO": "VILA NETINHO",
        "DATA DE NASCIMENTO": "1989-09-04",
        "CELULAR": "14988364517",
        "E-MAIL": "CRISBUBELA04@GMAIL.COM"
    },
    {
        "NOME": "FABIO LENOTTI DOS SANTOS",
        "CLUBE": "BORACEIA KADIMA",
        "IGREJA": "BORACÉIA",
        "DISTRITO": "VILA NETINHO",
        "DATA DE NASCIMENTO": "1980-09-05",
        "CELULAR": "11.972.758.978",
        "E-MAIL": "FABIO.DESBRAVADOR@HOTMAIL.COM"
    },
    {
        "NOME": "AGNALDO DA SILVA",
        "CLUBE": "DYNAMIS",
        "IGREJA": "JD. BOM RETIRO/SUMARE",
        "DISTRITO": "VILA NOVA APARECIDA",
        "DATA DE NASCIMENTO": "1975-08-07",
        "CELULAR": "(19) 982858833",
        "E-MAIL": "AGNALDO@GMAIL.COM"
    },
    {
        "NOME": "MISAEL FRANCISCO DOS PASSOS",
        "CLUBE": "MORIÁ",
        "IGREJA": "JD. DENADAI",
        "DISTRITO": "VILA NOVA APARECIDA",
        "DATA DE NASCIMENTO": "1983-06-08",
        "CELULAR": "(19) 8228-0163",
        "E-MAIL": "MISAREL@GMAIL.COM"
    },
    {
        "NOME": "CRISTIANO MONDIM SOARES",
        "CLUBE": "ASTHER",
        "IGREJA": "VILA NOVA APARECIDA",
        "DISTRITO": "VILA NOVA APARECIDA",
        "DATA DE NASCIMENTO": "1986-10-21",
        "CELULAR": "",
        "E-MAIL": "CRISTIANOMS86WEB@GMAIL.COM"
    },
    {
        "NOME": "EVERTON OLIVEIRA WEBER",
        "CLUBE": "LOUV-ART",
        "IGREJA": "LOUVEIRA",
        "DISTRITO": "VINHEDO",
        "DATA DE NASCIMENTO": "1970-09-04",
        "CELULAR": "81995441923",
        "E-MAIL": "EVERTON@GMAIL.COM"
    }
]